hmpnester/__init__.py
hmpnester-1.3.0.dist-info/METADATA
hmpnester-1.3.0.dist-info/RECORD
hmpnester-1.3.0.dist-info/WHEEL
hmpnester-1.3.0.dist-info/top_level.txt
