Metadata-Version: 2.1
Name: hmpnester
Version: 1.3.0
Summary: Tutorial package from HeadFirst series
Home-page: UNKNOWN
Author: hmperez
Author-email: betomperez@gmail.com
License: UNKNOWN
Platform: UNKNOWN
Classifier: Programming Language :: Python :: 3
Classifier: License :: OSI Approved :: MIT License
Classifier: Operating System :: OS Independent
